LICENSE.txt
README.md
setup.cfg
setup.py
scratchclient/Activity.py
scratchclient/Backpack.py
scratchclient/CloudConnection.py
scratchclient/Comment.py
scratchclient/Forums.py
scratchclient/Incomplete.py
scratchclient/Message.py
scratchclient/News.py
scratchclient/Project.py
scratchclient/Scraping.py
scratchclient/ScratchExceptions.py
scratchclient/ScratchSession.py
scratchclient/Studio.py
scratchclient/User.py
scratchclient/UserProfile.py
scratchclient/Websocket.py
scratchclient/__init__.py
scratchclient/__main__.py
scratchclient/util.py
scratchclient.egg-info/PKG-INFO
scratchclient.egg-info/SOURCES.txt
scratchclient.egg-info/dependency_links.txt
scratchclient.egg-info/requires.txt
scratchclient.egg-info/top_level.txt
test/test.py