Metadata-Version: 2.1
Name: scratchclient
Version: 1.0.0
Summary: A scratch API wrapper for Python.
Home-page: https://github.com/CubeyTheCube/scratchclient
Download-URL: https://github.com/CubeyTheCube/scratchclient/archive/v_10.0.tar.gz
Author: CubeyTheCube
Author-email: turtles142857@gmail.com
License: MIT
Keywords: scratch,api
Platform: UNKNOWN
Classifier: Development Status :: 4 - Beta
Classifier: Intended Audience :: Developers
Classifier: License :: OSI Approved :: MIT License
Classifier: Operating System :: OS Independent
Classifier: Programming Language :: Python :: 3
Classifier: Programming Language :: Python :: 3.6
Classifier: Programming Language :: Python :: 3.7
Provides-Extra: fast
License-File: LICENSE.txt
